s1_frame_enumerator/__init__.py
s1_frame_enumerator/exceptions.py
s1_frame_enumerator/ifg_enum.py
s1_frame_enumerator/s1_frames.py
s1_frame_enumerator/s1_stack.py
s1_frame_enumerator/s1_stack_formatter.py
s1_frame_enumerator/data/s1_frames_latitude_aligned.geojson.zip
s1_frame_enumerator/data/s1_gunw_frame_footprints.geojson.zip
s1_frame_enumerator-0.0.3.dist-info/licenses/LICENSE.txt
s1_frame_enumerator-0.0.3.dist-info/METADATA
s1_frame_enumerator-0.0.3.dist-info/WHEEL
s1_frame_enumerator-0.0.3.dist-info/top_level.txt
s1_frame_enumerator-0.0.3.dist-info/RECORD
