Metadata-Version: 2.4
Name: s1_frame_enumerator
Version: 0.0.3
Summary: Enumerate interferogram pairs from ARIA spatially fixed frames
Author: Charlie Marshak, David Bekaert, Joseph Kennedy, Sim Sangha, and ACCESS Team 
License: Apache-2.0
Project-URL: Homepage, https://github.com/ACCESS-Cloud-Based-InSAR/s1-frame-enumerator
Project-URL: Bug Tracker, https://github.com/ACCESS-Cloud-Based-InSAR/s1-frame-enumerator/issues
Classifier: Intended Audience :: Science/Research
Classifier: Natural Language :: English
Classifier: Operating System :: OS Independent
Classifier: Programming Language :: Python :: 3
Classifier: Programming Language :: Python :: 3.11
Classifier: Programming Language :: Python :: 3.12
Classifier: Programming Language :: Python :: 3.13
Requires-Python: >=3.11
License-File: LICENSE.txt
Requires-Dist: geopandas
Requires-Dist: pandas
Requires-Dist: asf_search
Requires-Dist: tqdm
Requires-Dist: requests
Requires-Dist: rasterio
Requires-Dist: shapely>=2.0
Provides-Extra: develop
Requires-Dist: pytest; extra == "develop"
Requires-Dist: pytest-cov; extra == "develop"
Requires-Dist: flake8; extra == "develop"
Requires-Dist: flake8-import-order; extra == "develop"
Requires-Dist: flake8-blind-except; extra == "develop"
Requires-Dist: flake8-builtins; extra == "develop"
Dynamic: license-file
